odoo10_addon_product_country_restriction-10.0.1.1.1.99.dev3-py3.8-nspkg.pth
odoo/addons/product_country_restriction/README.rst
odoo/addons/product_country_restriction/__init__.py
odoo/addons/product_country_restriction/__manifest__.py
odoo/addons/product_country_restriction/data/product_country_restriction_rule.xml
odoo/addons/product_country_restriction/demo/product_country_restriction.xml
odoo/addons/product_country_restriction/i18n/product_country_restriction.pot
odoo/addons/product_country_restriction/models/__init__.py
odoo/addons/product_country_restriction/models/country_restriction_mixin.py
odoo/addons/product_country_restriction/models/product_country_restriction.py
odoo/addons/product_country_restriction/models/product_country_restriction_item.py
odoo/addons/product_country_restriction/models/product_country_restriction_rule.py
odoo/addons/product_country_restriction/models/product_product.py
odoo/addons/product_country_restriction/models/product_template.py
odoo/addons/product_country_restriction/models/res_company.py
odoo/addons/product_country_restriction/models/res_country.py
odoo/addons/product_country_restriction/models/res_partner.py
odoo/addons/product_country_restriction/readme/CONTRIBUTORS.rst
odoo/addons/product_country_restriction/readme/DESCRIPTION.rst
odoo/addons/product_country_restriction/readme/HISTORY.rst
odoo/addons/product_country_restriction/readme/USAGE.rst
odoo/addons/product_country_restriction/security/product_country_restriction.xml
odoo/addons/product_country_restriction/static/description/icon.png
odoo/addons/product_country_restriction/static/description/index.html
odoo/addons/product_country_restriction/tests/__init__.py
odoo/addons/product_country_restriction/tests/common.py
odoo/addons/product_country_restriction/tests/test_country_restriction.py
odoo/addons/product_country_restriction/views/product_country_restriction.xml
odoo/addons/product_country_restriction/views/product_country_restriction_item.xml
odoo10_addon_product_country_restriction-10.0.1.1.1.99.dev3.dist-info/METADATA
odoo10_addon_product_country_restriction-10.0.1.1.1.99.dev3.dist-info/WHEEL
odoo10_addon_product_country_restriction-10.0.1.1.1.99.dev3.dist-info/namespace_packages.txt
odoo10_addon_product_country_restriction-10.0.1.1.1.99.dev3.dist-info/top_level.txt
odoo10_addon_product_country_restriction-10.0.1.1.1.99.dev3.dist-info/RECORD
