Metadata-Version: 2.1
Name: odoo10-addon-product-country-restriction
Version: 10.0.1.1.1.99.dev3
Summary: Allows to define product restrictions country based
Home-page: https://github.com/OCA/product-attribute
Author: ACSONE SA/NV,Odoo Community Association (OCA)
Author-email: support@odoo-community.org
License: AGPL-3
Platform: UNKNOWN
Classifier: Programming Language :: Python
Classifier: Framework :: Odoo
Classifier: Framework :: Odoo :: 10.0
Classifier: License :: OSI Approved :: GNU Affero General Public License v3
Classifier: Development Status :: 3 - Alpha
Requires-Python: ~=2.7
Requires-Dist: odoo <10.1dev,>=10.0
